ChatbotVerse/__init__.py
ChatbotVerse/chatbotVerse.py
ChatbotVerse-0.0.2.dist-info/LICENSE.txt
ChatbotVerse-0.0.2.dist-info/METADATA
ChatbotVerse-0.0.2.dist-info/WHEEL
ChatbotVerse-0.0.2.dist-info/top_level.txt
ChatbotVerse-0.0.2.dist-info/RECORD
